Compiled from "BottomPanelManager.kt"
public final class com.wuxianggujun.tinaide.ui.BottomPanelManager {
  private final androidx.fragment.app.FragmentActivity activity;

  private final android.view.ViewGroup container;

  private final kotlin.jvm.functions.Function0<kotlin.Unit> onCompile;

  private final kotlin.jvm.functions.Function0<kotlin.Unit> onStop;

  private final kotlin.jvm.functions.Function0<kotlin.Unit> onOpenOutput;

  private final kotlin.jvm.functions.Function1<com.wuxianggujun.tinaide.lsp.model.Diagnostic, kotlin.Unit> onDiagnosticClick;

  private final kotlin.jvm.functions.Function1<java.lang.String, kotlin.Unit> onSymbolClick;

  private final com.wuxianggujun.tinaide.databinding.BottomSheetPanelV2Binding binding;

  private final com.google.android.material.bottomsheet.BottomSheetBehavior<?> bottomSheetBehavior;

  private final android.view.GestureDetector gestureDetector;

  private com.wuxianggujun.tinaide.ui.fragment.BuildLogFragment buildLogFragment;

  private com.wuxianggujun.tinaide.ui.fragment.GeneralLogFragment generalLogFragment;

  private com.wuxianggujun.tinaide.ui.fragment.DiagnosticsFragment diagnosticsFragment;

  private boolean buildSucceeded;

  private com.wuxianggujun.tinaide.lsp.LspService$InitializationListener initListener;

  private com.wuxianggujun.tinaide.lsp.LspService$HealthListener healthListener;

  public com.wuxianggujun.tinaide.ui.BottomPanelManager(androidx.fragment.app.FragmentActivity, android.view.ViewGroup, kotlin.jvm.functions.Function0<kotlin.Unit>, kotlin.jvm.functions.Function0<kotlin.Unit>, kotlin.jvm.functions.Function0<kotlin.Unit>, kotlin.jvm.functions.Function1<? super com.wuxianggujun.tinaide.lsp.model.Diagnostic, kotlin.Unit>, kotlin.jvm.functions.Function1<? super java.lang.String, kotlin.Unit>);
    Code:
       0: aload_1
       1: ldc           #10                 // String activity
       3: invokestatic  #16                 // Method kotlin/jvm/internal/Intrinsics.checkNotNullParameter:(Ljava/lang/Object;Ljava/lang/String;)V
       6: aload_2
       7: ldc           #18                 // String container
       9: invokestatic  #16                 // Method kotlin/jvm/internal/Intrinsics.checkNotNullParameter:(Ljava/lang/Object;Ljava/lang/String;)V
      12: aload_3
      13: ldc           #20                 // String onCompile
      15: invokestatic  #16                 // Method kotlin/jvm/internal/Intrinsics.checkNotNullParameter:(Ljava/lang/Object;Ljava/lang/String;)V
      18: aload         4
      20: ldc           #22                 // String onStop
      22: invokestatic  #16                 // Method kotlin/jvm/internal/Intrinsics.checkNotNullParameter:(Ljava/lang/Object;Ljava/lang/String;)V
      25: aload         5
      27: ldc           #24                 // String onOpenOutput
      29: invokestatic  #16                 // Method kotlin/jvm/internal/Intrinsics.checkNotNullParameter:(Ljava/lang/Object;Ljava/lang/String;)V
      32: aload         6
      34: ldc           #26                 // String onDiagnosticClick
      36: invokestatic  #16                 // Method kotlin/jvm/internal/Intrinsics.checkNotNullParameter:(Ljava/lang/Object;Ljava/lang/String;)V
      39: aload         7
      41: ldc           #28                 // String onSymbolClick
      43: invokestatic  #16                 // Method kotlin/jvm/internal/Intrinsics.checkNotNullParameter:(Ljava/lang/Object;Ljava/lang/String;)V
      46: aload_0
      47: invokespecial #31                 // Method java/lang/Object."<init>":()V
      50: aload_0
      51: aload_1
      52: putfield      #34                 // Field activity:Landroidx/fragment/app/FragmentActivity;
      55: aload_0
      56: aload_2
      57: putfield      #37                 // Field container:Landroid/view/ViewGroup;
      60: aload_0
      61: aload_3
      62: putfield      #40                 // Field onCompile:Lkotlin/jvm/functions/Function0;
      65: aload_0
      66: aload         4
      68: putfield      #42                 // Field onStop:Lkotlin/jvm/functions/Function0;
      71: aload_0
      72: aload         5
      74: putfield      #44                 // Field onOpenOutput:Lkotlin/jvm/functions/Function0;
      77: aload_0
      78: aload         6
      80: putfield      #47                 // Field onDiagnosticClick:Lkotlin/jvm/functions/Function1;
      83: aload_0
      84: aload         7
      86: putfield      #49                 // Field onSymbolClick:Lkotlin/jvm/functions/Function1;
      89: nop
      90: aload_0
      91: aload_0
      92: getfield      #37                 // Field container:Landroid/view/ViewGroup;
      95: invokevirtual #55                 // Method android/view/ViewGroup.getContext:()Landroid/content/Context;
      98: invokestatic  #61                 // Method android/view/LayoutInflater.from:(Landroid/content/Context;)Landroid/view/LayoutInflater;
     101: aload_0
     102: getfield      #37                 // Field container:Landroid/view/ViewGroup;
     105: iconst_1
     106: invokestatic  #67                 // Method com/wuxianggujun/tinaide/databinding/BottomSheetPanelV2Binding.inflate:(Landroid/view/LayoutInflater;Landroid/view/ViewGroup;Z)Lcom/wuxianggujun/tinaide/databinding/BottomSheetPanelV2Binding;
     109: dup
     110: ldc           #69                 // String inflate(...)
     112: invokestatic  #72                 // Method kotlin/jvm/internal/Intrinsics.checkNotNullExpressionValue:(Ljava/lang/Object;Ljava/lang/String;)V
     115: putfield      #76                 // Field binding:Lcom/wuxianggujun/tinaide/databinding/BottomSheetPanelV2Binding;
     118: aload_0
     119: aload_0
     120: getfield      #76                 // Field binding:Lcom/wuxianggujun/tinaide/databinding/BottomSheetPanelV2Binding;
     123: getfield      #80                 // Field com/wuxianggujun/tinaide/databinding/BottomSheetPanelV2Binding.bottomSheet:Landroid/widget/LinearLayout;
     126: checkcast     #82                 // class android/view/View
     129: invokestatic  #87                 // Method com/google/android/material/bottomsheet/BottomSheetBehavior.from:(Landroid/view/View;)Lcom/google/android/material/bottomsheet/BottomSheetBehavior;
     132: astore        8
     134: aload         8
     136: astore        9
     138: astore        11
     140: iconst_0
     141: istore        10
     143: aload         9
     145: aload_0
     146: bipush        48
     148: invokespecial #91                 // Method dpToPx:(I)I
     151: invokevirtual #95                 // Method com/google/android/material/bottomsheet/BottomSheetBehavior.setPeekHeight:(I)V
     154: aload         9
     156: iconst_0
     157: invokevirtual #99                 // Method com/google/android/material/bottomsheet/BottomSheetBehavior.setHideable:(Z)V
     160: aload         9
     162: iconst_0
     163: invokevirtual #102                // Method com/google/android/material/bottomsheet/BottomSheetBehavior.setFitToContents:(Z)V
     166: aload         9
     168: ldc           #103                // float 0.5f
     170: invokevirtual #107                // Method com/google/android/material/bottomsheet/BottomSheetBehavior.setHalfExpandedRatio:(F)V
     173: aload         9
     175: iconst_4
     176: invokevirtual #110                // Method com/google/android/material/bottomsheet/BottomSheetBehavior.setState:(I)V
     179: nop
     180: aload         11
     182: aload         8
     184: dup
     185: ldc           #112                // String apply(...)
     187: invokestatic  #72                 // Method kotlin/jvm/internal/Intrinsics.checkNotNullExpressionValue:(Ljava/lang/Object;Ljava/lang/String;)V
     190: putfield      #116                // Field bottomSheetBehavior:Lcom/google/android/material/bottomsheet/BottomSheetBehavior;
     193: aload_0
     194: new           #118                // class android/view/GestureDetector
     197: dup
     198: aload_0
     199: getfield      #37                 // Field container:Landroid/view/ViewGroup;
     202: invokevirtual #55                 // Method android/view/ViewGroup.getContext:()Landroid/content/Context;
     205: new           #120                // class com/wuxianggujun/tinaide/ui/BottomPanelManager$SwipeGestureListener
     208: dup
     209: aload_0
     210: invokespecial #123                // Method com/wuxianggujun/tinaide/ui/BottomPanelManager$SwipeGestureListener."<init>":(Lcom/wuxianggujun/tinaide/ui/BottomPanelManager;)V
     213: checkcast     #125                // class android/view/GestureDetector$OnGestureListener
     216: invokespecial #128                // Method android/view/GestureDetector."<init>":(Landroid/content/Context;Landroid/view/GestureDetector$OnGestureListener;)V
     219: putfield      #132                // Field gestureDetector:Landroid/view/GestureDetector;
     222: aload_0
     223: invokespecial #135                // Method setupSymbolBar:()V
     226: aload_0
     227: invokespecial #138                // Method setupTabs:()V
     230: aload_0
     231: invokespecial #141                // Method setupGestureDetector:()V
     234: aload_0
     235: invokespecial #144                // Method setupLspStatus:()V
     238: aload_0
     239: invokespecial #147                // Method setupBottomSheetCallback:()V
     242: nop
     243: return

  public com.wuxianggujun.tinaide.ui.BottomPanelManager(androidx.fragment.app.FragmentActivity, android.view.ViewGroup, kotlin.jvm.functions.Function0, kotlin.jvm.functions.Function0, kotlin.jvm.functions.Function0, kotlin.jvm.functions.Function1, kotlin.jvm.functions.Function1, int, kotlin.jvm.internal.DefaultConstructorMarker);
    Code:
       0: iload         8
       2: iconst_4
       3: iand
       4: ifeq          13
       7: invokedynamic #172,  0            // InvokeDynamic #0:invoke:()Lkotlin/jvm/functions/Function0;
      12: astore_3
      13: iload         8
      15: bipush        8
      17: iand
      18: ifeq          28
      21: invokedynamic #177,  0            // InvokeDynamic #1:invoke:()Lkotlin/jvm/functions/Function0;
      26: astore        4
      28: iload         8
      30: bipush        16
      32: iand
      33: ifeq          43
      36: invokedynamic #182,  0            // InvokeDynamic #2:invoke:()Lkotlin/jvm/functions/Function0;
      41: astore        5
      43: iload         8
      45: bipush        32
      47: iand
      48: ifeq          58
      51: invokedynamic #193,  0            // InvokeDynamic #3:invoke:()Lkotlin/jvm/functions/Function1;
      56: astore        6
      58: iload         8
      60: bipush        64
      62: iand
      63: ifeq          73
      66: invokedynamic #200,  0            // InvokeDynamic #4:invoke:()Lkotlin/jvm/functions/Function1;
      71: astore        7
      73: aload_0
      74: aload_1
      75: aload_2
      76: aload_3
      77: aload         4
      79: aload         5
      81: aload         6
      83: aload         7
      85: invokespecial #202                // Method "<init>":(Landroidx/fragment/app/FragmentActivity;Landroid/view/ViewGroup;Lkotlin/jvm/functions/Function0;Lkotlin/jvm/functions/Function0;Lkotlin/jvm/functions/Function0;Lkotlin/jvm/functions/Function1;Lkotlin/jvm/functions/Function1;)V
      88: return

  private final void setupBottomSheetCallback();
    Code:
       0: aload_0
       1: getfield      #116                // Field bottomSheetBehavior:Lcom/google/android/material/bottomsheet/BottomSheetBehavior;
       4: new           #204                // class com/wuxianggujun/tinaide/ui/BottomPanelManager$setupBottomSheetCallback$1
       7: dup
       8: aload_0
       9: invokespecial #205                // Method com/wuxianggujun/tinaide/ui/BottomPanelManager$setupBottomSheetCallback$1."<init>":(Lcom/wuxianggujun/tinaide/ui/BottomPanelManager;)V
      12: checkcast     #207                // class com/google/android/material/bottomsheet/BottomSheetBehavior$BottomSheetCallback
      15: invokevirtual #211                // Method com/google/android/material/bottomsheet/BottomSheetBehavior.addBottomSheetCallback:(Lcom/google/android/material/bottomsheet/BottomSheetBehavior$BottomSheetCallback;)V
      18: return

  private final void notifyLogViewsVisibility(boolean);
    Code:
       0: iload_1
       1: ifeq          136
       4: aload_0
       5: getfield      #76                 // Field binding:Lcom/wuxianggujun/tinaide/databinding/BottomSheetPanelV2Binding;
       8: getfield      #216                // Field com/wuxianggujun/tinaide/databinding/BottomSheetPanelV2Binding.viewPager:Landroidx/viewpager2/widget/ViewPager2;
      11: invokevirtual #222                // Method androidx/viewpager2/widget/ViewPager2.getCurrentItem:()I
      14: tableswitch   { // 0 to 1
                     0: 36
                     1: 86
               default: 133
          }
      36: aload_0
      37: getfield      #226                // Field buildLogFragment:Lcom/wuxianggujun/tinaide/ui/fragment/BuildLogFragment;
      40: ifnull        230
      43: aload_0
      44: getfield      #226                // Field buildLogFragment:Lcom/wuxianggujun/tinaide/ui/fragment/BuildLogFragment;
      47: dup
      48: ifnonnull     58
      51: pop
      52: ldc           #227                // String buildLogFragment
      54: invokestatic  #231                // Method kotlin/jvm/internal/Intrinsics.throwUninitializedPropertyAccessException:(Ljava/lang/String;)V
      57: aconst_null
      58: invokevirtual #237                // Method com/wuxianggujun/tinaide/ui/fragment/BuildLogFragment.isAdded:()Z
      61: ifeq          230
      64: aload_0
      65: getfield      #226                // Field buildLogFragment:Lcom/wuxianggujun/tinaide/ui/fragment/BuildLogFragment;
      68: dup
      69: ifnonnull     79
      72: pop
      73: ldc           #227                // String buildLogFragment
      75: invokestatic  #231                // Method kotlin/jvm/internal/Intrinsics.throwUninitializedPropertyAccessException:(Ljava/lang/String;)V
      78: aconst_null
      79: iconst_1
      80: invokevirtual #240                // Method com/wuxianggujun/tinaide/ui/fragment/BuildLogFragment.notifyVisibilityChanged:(Z)V
      83: goto          230
      86: aload_0
      87: getfield      #244                // Field generalLogFragment:Lcom/wuxianggujun/tinaide/ui/fragment/GeneralLogFragment;
      90: ifnull        230
      93: aload_0
      94: getfield      #244                // Field generalLogFragment:Lcom/wuxianggujun/tinaide/ui/fragment/GeneralLogFragment;
      97: dup
      98: ifnonnull     108
     101: pop
     102: ldc           #245                // String generalLogFragment
     104: invokestatic  #231                // Method kotlin/jvm/internal/Intrinsics.throwUninitializedPropertyAccessException:(Ljava/lang/String;)V
     107: aconst_null
     108: invokevirtual #248                // Method com/wuxianggujun/tinaide/ui/fragment/GeneralLogFragment.isAdded:()Z
     111: ifeq          230
     114: aload_0
     115: getfield      #244                // Field generalLogFragment:Lcom/wuxianggujun/tinaide/ui/fragment/GeneralLogFragment;
     118: dup
     119: ifnonnull     129
     122: pop
     123: ldc           #245                // String generalLogFragment
     125: invokestatic  #231                // Method kotlin/jvm/internal/Intrinsics.throwUninitializedPropertyAccessException:(Ljava/lang/String;)V
     128: aconst_null
     129: iconst_1
     130: invokevirtual #249                // Method com/wuxianggujun/tinaide/ui/fragment/GeneralLogFragment.notifyVisibilityChanged:(Z)V
     133: goto          230
     136: aload_0
     137: getfield      #226                // Field buildLogFragment:Lcom/wuxianggujun/tinaide/ui/fragment/BuildLogFragment;
     140: ifnull        183
     143: aload_0
     144: getfield      #226                // Field buildLogFragment:Lcom/wuxianggujun/tinaide/ui/fragment/BuildLogFragment;
     147: dup
     148: ifnonnull     158
     151: pop
     152: ldc           #227                // String buildLogFragment
     154: invokestatic  #231                // Method kotlin/jvm/internal/Intrinsics.throwUninitializedPropertyAccessException:(Ljava/lang/String;)V
     157: aconst_null
     158: invokevirtual #237                // Method com/wuxianggujun/tinaide/ui/fragment/BuildLogFragment.isAdded:()Z
     161: ifeq          183
     164: aload_0
     165: getfield      #226                // Field buildLogFragment:Lcom/wuxianggujun/tinaide/ui/fragment/BuildLogFragment;
     168: dup
     169: ifnonnull     179
     172: pop
     173: ldc           #227                // String buildLogFragment
     175: invokestatic  #231                // Method kotlin/jvm/internal/Intrinsics.throwUninitializedPropertyAccessException:(Ljava/lang/String;)V
     178: aconst_null
     179: iconst_0
     180: invokevirtual #240                // Method com/wuxianggujun/tinaide/ui/fragment/BuildLogFragment.notifyVisibilityChanged:(Z)V
     183: aload_0
     184: getfield      #244                // Field generalLogFragment:Lcom/wuxianggujun/tinaide/ui/fragment/GeneralLogFragment;
     187: ifnull        230
     190: aload_0
     191: getfield      #244                // Field generalLogFragment:Lcom/wuxianggujun/tinaide/ui/fragment/GeneralLogFragment;
     194: dup
     195: ifnonnull     205
     198: pop
     199: ldc           #245                // String generalLogFragment
     201: invokestatic  #231                // Method kotlin/jvm/internal/Intrinsics.throwUninitializedPropertyAccessException:(Ljava/lang/String;)V
     204: aconst_null
     205: invokevirtual #248                // Method com/wuxianggujun/tinaide/ui/fragment/GeneralLogFragment.isAdded:()Z
     208: ifeq          230
     211: aload_0
     212: getfield      #244                // Field generalLogFragment:Lcom/wuxianggujun/tinaide/ui/fragment/GeneralLogFragment;
     215: dup
     216: ifnonnull     226
     219: pop
     220: ldc           #245                // String generalLogFragment
     222: invokestatic  #231                // Method kotlin/jvm/internal/Intrinsics.throwUninitializedPropertyAccessException:(Ljava/lang/String;)V
     225: aconst_null
     226: iconst_0
     227: invokevirtual #249                // Method com/wuxianggujun/tinaide/ui/fragment/GeneralLogFragment.notifyVisibilityChanged:(Z)V
     230: return

  private final void setupSymbolBar();
    Code:
       0: aload_0
       1: getfield      #76                 // Field binding:Lcom/wuxianggujun/tinaide/databinding/BottomSheetPanelV2Binding;
       4: getfield      #255                // Field com/wuxianggujun/tinaide/databinding/BottomSheetPanelV2Binding.symbolInputBar:Lcom/wuxianggujun/tinaide/ui/SymbolInputBar;
       7: aload_0
       8: invokedynamic #263,  0            // InvokeDynamic #5:invoke:(Lcom/wuxianggujun/tinaide/ui/BottomPanelManager;)Lkotlin/jvm/functions/Function1;
      13: invokevirtual #269                // Method com/wuxianggujun/tinaide/ui/SymbolInputBar.setOnSymbolClickListener:(Lkotlin/jvm/functions/Function1;)V
      16: return

  private final void setupTabs();
    Code:
       0: aload_0
       1: getstatic     #273                // Field com/wuxianggujun/tinaide/ui/fragment/BuildLogFragment.Companion:Lcom/wuxianggujun/tinaide/ui/fragment/BuildLogFragment$Companion;
       4: aload_0
       5: getfield      #40                 // Field onCompile:Lkotlin/jvm/functions/Function0;
       8: aload_0
       9: getfield      #42                 // Field onStop:Lkotlin/jvm/functions/Function0;
      12: aload_0
      13: invokedynamic #281,  0            // InvokeDynamic #6:invoke:(Lcom/wuxianggujun/tinaide/ui/BottomPanelManager;)Lkotlin/jvm/functions/Function0;
      18: invokevirtual #287                // Method com/wuxianggujun/tinaide/ui/fragment/BuildLogFragment$Companion.newInstance:(Lkotlin/jvm/functions/Function0;Lkotlin/jvm/functions/Function0;Lkotlin/jvm/functions/Function0;)Lcom/wuxianggujun/tinaide/ui/fragment/BuildLogFragment;
      21: putfield      #226                // Field buildLogFragment:Lcom/wuxianggujun/tinaide/ui/fragment/BuildLogFragment;
      24: aload_0
      25: getstatic     #290                // Field com/wuxianggujun/tinaide/ui/fragment/GeneralLogFragment.Companion:Lcom/wuxianggujun/tinaide/ui/fragment/GeneralLogFragment$Companion;
      28: invokevirtual #295                // Method com/wuxianggujun/tinaide/ui/fragment/GeneralLogFragment$Companion.newInstance:()Lcom/wuxianggujun/tinaide/ui/fragment/GeneralLogFragment;
      31: putfield      #244                // Field generalLogFragment:Lcom/wuxianggujun/tinaide/ui/fragment/GeneralLogFragment;
      34: aload_0
      35: getstatic     #300                // Field com/wuxianggujun/tinaide/ui/fragment/DiagnosticsFragment.Companion:Lcom/wuxianggujun/tinaide/ui/fragment/DiagnosticsFragment$Companion;
      38: aload_0
      39: getfield      #47                 // Field onDiagnosticClick:Lkotlin/jvm/functions/Function1;
      42: invokevirtual #305                // Method com/wuxianggujun/tinaide/ui/fragment/DiagnosticsFragment$Companion.newInstance:(Lkotlin/jvm/functions/Function1;)Lcom/wuxianggujun/tinaide/ui/fragment/DiagnosticsFragment;
      45: putfield      #309                // Field diagnosticsFragment:Lcom/wuxianggujun/tinaide/ui/fragment/DiagnosticsFragment;
      48: new           #311                // class com/wuxianggujun/tinaide/ui/BottomPanelManager$BottomPanelPagerAdapter
      51: dup
      52: aload_0
      53: aload_0
      54: getfield      #34                 // Field activity:Landroidx/fragment/app/FragmentActivity;
      57: invokespecial #314                // Method com/wuxianggujun/tinaide/ui/BottomPanelManager$BottomPanelPagerAdapter."<init>":(Lcom/wuxianggujun/tinaide/ui/BottomPanelManager;Landroidx/fragment/app/FragmentActivity;)V
      60: astore_1
      61: aload_0
      62: getfield      #76                 // Field binding:Lcom/wuxianggujun/tinaide/databinding/BottomSheetPanelV2Binding;
      65: getfield      #216                // Field com/wuxianggujun/tinaide/databinding/BottomSheetPanelV2Binding.viewPager:Landroidx/viewpager2/widget/ViewPager2;
      68: aload_1
      69: checkcast     #316                // class androidx/recyclerview/widget/RecyclerView$Adapter
      72: invokevirtual #320                // Method androidx/viewpager2/widget/ViewPager2.setAdapter:(Landroidx/recyclerview/widget/RecyclerView$Adapter;)V
      75: aload_0
      76: getfield      #76                 // Field binding:Lcom/wuxianggujun/tinaide/databinding/BottomSheetPanelV2Binding;
      79: getfield      #216                // Field com/wuxianggujun/tinaide/databinding/BottomSheetPanelV2Binding.viewPager:Landroidx/viewpager2/widget/ViewPager2;
      82: iconst_0
      83: invokevirtual #323                // Method androidx/viewpager2/widget/ViewPager2.setUserInputEnabled:(Z)V
      86: new           #325                // class com/google/android/material/tabs/TabLayoutMediator
      89: dup
      90: aload_0
      91: getfield      #76                 // Field binding:Lcom/wuxianggujun/tinaide/databinding/BottomSheetPanelV2Binding;
      94: getfield      #329                // Field com/wuxianggujun/tinaide/databinding/BottomSheetPanelV2Binding.tabLayout:Lcom/google/android/material/tabs/TabLayout;
      97: aload_0
      98: getfield      #76                 // Field binding:Lcom/wuxianggujun/tinaide/databinding/BottomSheetPanelV2Binding;
     101: getfield      #216                // Field com/wuxianggujun/tinaide/databinding/BottomSheetPanelV2Binding.viewPager:Landroidx/viewpager2/widget/ViewPager2;
     104: invokedynamic #339,  0            // InvokeDynamic #7:onConfigureTab:()Lcom/google/android/material/tabs/TabLayoutMediator$TabConfigurationStrategy;
     109: invokespecial #342                // Method com/google/android/material/tabs/TabLayoutMediator."<init>":(Lcom/google/android/material/tabs/TabLayout;Landroidx/viewpager2/widget/ViewPager2;Lcom/google/android/material/tabs/TabLayoutMediator$TabConfigurationStrategy;)V
     112: invokevirtual #345                // Method com/google/android/material/tabs/TabLayoutMediator.attach:()V
     115: return

  private final void setupLspStatus();
    Code:
       0: aload_0
       1: aload_0
       2: invokedynamic #357,  0            // InvokeDynamic #8:onInitializationChanged:(Lcom/wuxianggujun/tinaide/ui/BottomPanelManager;)Lcom/wuxianggujun/tinaide/lsp/LspService$InitializationListener;
       7: putfield      #361                // Field initListener:Lcom/wuxianggujun/tinaide/lsp/LspService$InitializationListener;
      10: aload_0
      11: aload_0
      12: invokedynamic #372,  0            // InvokeDynamic #9:onHealthEvent:(Lcom/wuxianggujun/tinaide/ui/BottomPanelManager;)Lcom/wuxianggujun/tinaide/lsp/LspService$HealthListener;
      17: putfield      #376                // Field healthListener:Lcom/wuxianggujun/tinaide/lsp/LspService$HealthListener;
      20: aload_0
      21: getfield      #361                // Field initListener:Lcom/wuxianggujun/tinaide/lsp/LspService$InitializationListener;
      24: dup
      25: ifnull        41
      28: astore_2
      29: iconst_0
      30: istore_3
      31: getstatic     #382                // Field com/wuxianggujun/tinaide/lsp/LspService.INSTANCE:Lcom/wuxianggujun/tinaide/lsp/LspService;
      34: aload_2
      35: invokevirtual #386                // Method com/wuxianggujun/tinaide/lsp/LspService.addInitializationListener:(Lcom/wuxianggujun/tinaide/lsp/LspService$InitializationListener;)V
      38: goto          43
      41: pop
      42: nop
      43: aload_0
      44: getfield      #376                // Field healthListener:Lcom/wuxianggujun/tinaide/lsp/LspService$HealthListener;
      47: dup
      48: ifnull        64
      51: astore_2
      52: iconst_0
      53: istore_3
      54: getstatic     #382                // Field com/wuxianggujun/tinaide/lsp/LspService.INSTANCE:Lcom/wuxianggujun/tinaide/lsp/LspService;
      57: aload_2
      58: invokevirtual #390                // Method com/wuxianggujun/tinaide/lsp/LspService.addHealthListener:(Lcom/wuxianggujun/tinaide/lsp/LspService$HealthListener;)V
      61: goto          66
      64: pop
      65: nop
      66: getstatic     #382                // Field com/wuxianggujun/tinaide/lsp/LspService.INSTANCE:Lcom/wuxianggujun/tinaide/lsp/LspService;
      69: invokevirtual #393                // Method com/wuxianggujun/tinaide/lsp/LspService.isInitialized:()Z
      72: istore_1
      73: aload_0
      74: iload_1
      75: ldc_w         #395                // String LSP
      78: invokespecial #399                // Method updateLspStatus:(ZLjava/lang/String;)V
      81: return

  private final void updateLspStatus(boolean, java.lang.String);
    Code:
       0: aload_0
       1: getfield      #76                 // Field binding:Lcom/wuxianggujun/tinaide/databinding/BottomSheetPanelV2Binding;
       4: invokevirtual #411                // Method com/wuxianggujun/tinaide/databinding/BottomSheetPanelV2Binding.getRoot:()Landroidx/coordinatorlayout/widget/CoordinatorLayout;
       7: invokevirtual #414                // Method androidx/coordinatorlayout/widget/CoordinatorLayout.getContext:()Landroid/content/Context;
      10: astore_3
      11: iload_1
      12: ifeq          25
      15: aload_3
      16: getstatic     #419                // Field com/wuxianggujun/tinaide/R$color.lspStatusConnected:I
      19: invokestatic  #425                // Method androidx/core/content/ContextCompat.getColor:(Landroid/content/Context;I)I
      22: goto          32
      25: aload_3
      26: getstatic     #428                // Field com/wuxianggujun/tinaide/R$color.lspStatusDisconnected:I
      29: invokestatic  #425                // Method androidx/core/content/ContextCompat.getColor:(Landroid/content/Context;I)I
      32: istore        4
      34: aload_0
      35: getfield      #76                 // Field binding:Lcom/wuxianggujun/tinaide/databinding/BottomSheetPanelV2Binding;
      38: getfield      #432                // Field com/wuxianggujun/tinaide/databinding/BottomSheetPanelV2Binding.lspStatusIndicator:Landroid/view/View;
      41: iload         4
      43: invokestatic  #438                // Method android/content/res/ColorStateList.valueOf:(I)Landroid/content/res/ColorStateList;
      46: invokevirtual #442                // Method android/view/View.setBackgroundTintList:(Landroid/content/res/ColorStateList;)V
      49: aload_0
      50: getfield      #76                 // Field binding:Lcom/wuxianggujun/tinaide/databinding/BottomSheetPanelV2Binding;
      53: getfield      #446                // Field com/wuxianggujun/tinaide/databinding/BottomSheetPanelV2Binding.tvLspStatus:Landroid/widget/TextView;
      56: aload_2
      57: checkcast     #448                // class java/lang/CharSequence
      60: invokevirtual #454                // Method android/widget/TextView.setText:(Ljava/lang/CharSequence;)V
      63: return

  private final void setupGestureDetector();
    Code:
       0: aload_0
       1: getfield      #76                 // Field binding:Lcom/wuxianggujun/tinaide/databinding/BottomSheetPanelV2Binding;
       4: getfield      #255                // Field com/wuxianggujun/tinaide/databinding/BottomSheetPanelV2Binding.symbolInputBar:Lcom/wuxianggujun/tinaide/ui/SymbolInputBar;
       7: aload_0
       8: invokedynamic #473,  0            // InvokeDynamic #10:onTouch:(Lcom/wuxianggujun/tinaide/ui/BottomPanelManager;)Landroid/view/View$OnTouchListener;
      13: invokevirtual #477                // Method com/wuxianggujun/tinaide/ui/SymbolInputBar.setOnTouchListener:(Landroid/view/View$OnTouchListener;)V
      16: return

  public final void appendBuildLog(com.wuxianggujun.tinaide.output.LogLevel, java.lang.String);
    Code:
       0: aload_1
       1: ldc_w         #481                // String level
       4: invokestatic  #16                 // Method kotlin/jvm/internal/Intrinsics.checkNotNullParameter:(Ljava/lang/Object;Ljava/lang/String;)V
       7: aload_2
       8: ldc_w         #482                // String message
      11: invokestatic  #16                 // Method kotlin/jvm/internal/Intrinsics.checkNotNullParameter:(Ljava/lang/Object;Ljava/lang/String;)V
      14: aload_0
      15: getfield      #226                // Field buildLogFragment:Lcom/wuxianggujun/tinaide/ui/fragment/BuildLogFragment;
      18: ifnull        80
      21: aload_0
      22: getfield      #226                // Field buildLogFragment:Lcom/wuxianggujun/tinaide/ui/fragment/BuildLogFragment;
      25: dup
      26: ifnonnull     36
      29: pop
      30: ldc           #227                // String buildLogFragment
      32: invokestatic  #231                // Method kotlin/jvm/internal/Intrinsics.throwUninitializedPropertyAccessException:(Ljava/lang/String;)V
      35: aconst_null
      36: invokevirtual #237                // Method com/wuxianggujun/tinaide/ui/fragment/BuildLogFragment.isAdded:()Z
      39: ifeq          80
      42: aload_0
      43: getfield      #226                // Field buildLogFragment:Lcom/wuxianggujun/tinaide/ui/fragment/BuildLogFragment;
      46: dup
      47: ifnonnull     57
      50: pop
      51: ldc           #227                // String buildLogFragment
      53: invokestatic  #231                // Method kotlin/jvm/internal/Intrinsics.throwUninitializedPropertyAccessException:(Ljava/lang/String;)V
      56: aconst_null
      57: invokevirtual #486                // Method com/wuxianggujun/tinaide/ui/fragment/BuildLogFragment.getView:()Landroid/view/View;
      60: dup
      61: ifnull        79
      64: aload_0
      65: aload_1
      66: aload_2
      67: invokedynamic #496,  0            // InvokeDynamic #11:run:(Lcom/wuxianggujun/tinaide/ui/BottomPanelManager;Lcom/wuxianggujun/tinaide/output/LogLevel;Ljava/lang/String;)Ljava/lang/Runnable;
      72: invokevirtual #500                // Method android/view/View.post:(Ljava/lang/Runnable;)Z
      75: pop
      76: goto          80
      79: pop
      80: return

  public final void appendGeneralLog(com.wuxianggujun.tinaide.output.LogLevel, java.lang.String);
    Code:
       0: aload_1
       1: ldc_w         #481                // String level
       4: invokestatic  #16                 // Method kotlin/jvm/internal/Intrinsics.checkNotNullParameter:(Ljava/lang/Object;Ljava/lang/String;)V
       7: aload_2
       8: ldc_w         #482                // String message
      11: invokestatic  #16                 // Method kotlin/jvm/internal/Intrinsics.checkNotNullParameter:(Ljava/lang/Object;Ljava/lang/String;)V
      14: aload_0
      15: getfield      #244                // Field generalLogFragment:Lcom/wuxianggujun/tinaide/ui/fragment/GeneralLogFragment;
      18: ifnull        80
      21: aload_0
      22: getfield      #244                // Field generalLogFragment:Lcom/wuxianggujun/tinaide/ui/fragment/GeneralLogFragment;
      25: dup
      26: ifnonnull     36
      29: pop
      30: ldc           #245                // String generalLogFragment
      32: invokestatic  #231                // Method kotlin/jvm/internal/Intrinsics.throwUninitializedPropertyAccessException:(Ljava/lang/String;)V
      35: aconst_null
      36: invokevirtual #248                // Method com/wuxianggujun/tinaide/ui/fragment/GeneralLogFragment.isAdded:()Z
      39: ifeq          80
      42: aload_0
      43: getfield      #244                // Field generalLogFragment:Lcom/wuxianggujun/tinaide/ui/fragment/GeneralLogFragment;
      46: dup
      47: ifnonnull     57
      50: pop
      51: ldc           #245                // String generalLogFragment
      53: invokestatic  #231                // Method kotlin/jvm/internal/Intrinsics.throwUninitializedPropertyAccessException:(Ljava/lang/String;)V
      56: aconst_null
      57: invokevirtual #503                // Method com/wuxianggujun/tinaide/ui/fragment/GeneralLogFragment.getView:()Landroid/view/View;
      60: dup
      61: ifnull        79
      64: aload_0
      65: aload_1
      66: aload_2
      67: invokedynamic #508,  0            // InvokeDynamic #12:run:(Lcom/wuxianggujun/tinaide/ui/BottomPanelManager;Lcom/wuxianggujun/tinaide/output/LogLevel;Ljava/lang/String;)Ljava/lang/Runnable;
      72: invokevirtual #500                // Method android/view/View.post:(Ljava/lang/Runnable;)Z
      75: pop
      76: goto          80
      79: pop
      80: return

  public final void clearBuildLog();
    Code:
       0: aload_0
       1: getfield      #226                // Field buildLogFragment:Lcom/wuxianggujun/tinaide/ui/fragment/BuildLogFragment;
       4: ifnull        64
       7: aload_0
       8: getfield      #226                // Field buildLogFragment:Lcom/wuxianggujun/tinaide/ui/fragment/BuildLogFragment;
      11: dup
      12: ifnonnull     22
      15: pop
      16: ldc           #227                // String buildLogFragment
      18: invokestatic  #231                // Method kotlin/jvm/internal/Intrinsics.throwUninitializedPropertyAccessException:(Ljava/lang/String;)V
      21: aconst_null
      22: invokevirtual #237                // Method com/wuxianggujun/tinaide/ui/fragment/BuildLogFragment.isAdded:()Z
      25: ifeq          64
      28: aload_0
      29: getfield      #226                // Field buildLogFragment:Lcom/wuxianggujun/tinaide/ui/fragment/BuildLogFragment;
      32: dup
      33: ifnonnull     43
      36: pop
      37: ldc           #227                // String buildLogFragment
      39: invokestatic  #231                // Method kotlin/jvm/internal/Intrinsics.throwUninitializedPropertyAccessException:(Ljava/lang/String;)V
      42: aconst_null
      43: invokevirtual #486                // Method com/wuxianggujun/tinaide/ui/fragment/BuildLogFragment.getView:()Landroid/view/View;
      46: dup
      47: ifnull        63
      50: aload_0
      51: invokedynamic #516,  0            // InvokeDynamic #13:run:(Lcom/wuxianggujun/tinaide/ui/BottomPanelManager;)Ljava/lang/Runnable;
      56: invokevirtual #500                // Method android/view/View.post:(Ljava/lang/Runnable;)Z
      59: pop
      60: goto          64
      63: pop
      64: return

  public final void clearGeneralLog();
    Code:
       0: aload_0
       1: getfield      #244                // Field generalLogFragment:Lcom/wuxianggujun/tinaide/ui/fragment/GeneralLogFragment;
       4: ifnull        64
       7: aload_0
       8: getfield      #244                // Field generalLogFragment:Lcom/wuxianggujun/tinaide/ui/fragment/GeneralLogFragment;
      11: dup
      12: ifnonnull     22
      15: pop
      16: ldc           #245                // String generalLogFragment
      18: invokestatic  #231                // Method kotlin/jvm/internal/Intrinsics.throwUninitializedPropertyAccessException:(Ljava/lang/String;)V
      21: aconst_null
      22: invokevirtual #248                // Method com/wuxianggujun/tinaide/ui/fragment/GeneralLogFragment.isAdded:()Z
      25: ifeq          64
      28: aload_0
      29: getfield      #244                // Field generalLogFragment:Lcom/wuxianggujun/tinaide/ui/fragment/GeneralLogFragment;
      32: dup
      33: ifnonnull     43
      36: pop
      37: ldc           #245                // String generalLogFragment
      39: invokestatic  #231                // Method kotlin/jvm/internal/Intrinsics.throwUninitializedPropertyAccessException:(Ljava/lang/String;)V
      42: aconst_null
      43: invokevirtual #503                // Method com/wuxianggujun/tinaide/ui/fragment/GeneralLogFragment.getView:()Landroid/view/View;
      46: dup
      47: ifnull        63
      50: aload_0
      51: invokedynamic #522,  0            // InvokeDynamic #14:run:(Lcom/wuxianggujun/tinaide/ui/BottomPanelManager;)Ljava/lang/Runnable;
      56: invokevirtual #500                // Method android/view/View.post:(Ljava/lang/Runnable;)Z
      59: pop
      60: goto          64
      63: pop
      64: return

  public final void setBuildSucceeded(boolean);
    Code:
       0: aload_0
       1: iload_1
       2: putfield      #526                // Field buildSucceeded:Z
       5: aload_0
       6: getfield      #226                // Field buildLogFragment:Lcom/wuxianggujun/tinaide/ui/fragment/BuildLogFragment;
       9: ifnull        70
      12: aload_0
      13: getfield      #226                // Field buildLogFragment:Lcom/wuxianggujun/tinaide/ui/fragment/BuildLogFragment;
      16: dup
      17: ifnonnull     27
      20: pop
      21: ldc           #227                // String buildLogFragment
      23: invokestatic  #231                // Method kotlin/jvm/internal/Intrinsics.throwUninitializedPropertyAccessException:(Ljava/lang/String;)V
      26: aconst_null
      27: invokevirtual #237                // Method com/wuxianggujun/tinaide/ui/fragment/BuildLogFragment.isAdded:()Z
      30: ifeq          70
      33: aload_0
      34: getfield      #226                // Field buildLogFragment:Lcom/wuxianggujun/tinaide/ui/fragment/BuildLogFragment;
      37: dup
      38: ifnonnull     48
      41: pop
      42: ldc           #227                // String buildLogFragment
      44: invokestatic  #231                // Method kotlin/jvm/internal/Intrinsics.throwUninitializedPropertyAccessException:(Ljava/lang/String;)V
      47: aconst_null
      48: invokevirtual #486                // Method com/wuxianggujun/tinaide/ui/fragment/BuildLogFragment.getView:()Landroid/view/View;
      51: dup
      52: ifnull        69
      55: aload_0
      56: iload_1
      57: invokedynamic #533,  0            // InvokeDynamic #15:run:(Lcom/wuxianggujun/tinaide/ui/BottomPanelManager;Z)Ljava/lang/Runnable;
      62: invokevirtual #500                // Method android/view/View.post:(Ljava/lang/Runnable;)Z
      65: pop
      66: goto          70
      69: pop
      70: return

  public final void expand();
    Code:
       0: aload_0
       1: getfield      #116                // Field bottomSheetBehavior:Lcom/google/android/material/bottomsheet/BottomSheetBehavior;
       4: iconst_3
       5: invokevirtual #110                // Method com/google/android/material/bottomsheet/BottomSheetBehavior.setState:(I)V
       8: return

  public final void collapse();
    Code:
       0: aload_0
       1: getfield      #116                // Field bottomSheetBehavior:Lcom/google/android/material/bottomsheet/BottomSheetBehavior;
       4: iconst_4
       5: invokevirtual #110                // Method com/google/android/material/bottomsheet/BottomSheetBehavior.setState:(I)V
       8: return

  public final void halfExpand();
    Code:
       0: aload_0
       1: getfield      #116                // Field bottomSheetBehavior:Lcom/google/android/material/bottomsheet/BottomSheetBehavior;
       4: bipush        6
       6: invokevirtual #110                // Method com/google/android/material/bottomsheet/BottomSheetBehavior.setState:(I)V
       9: return

  public final void switchToBuildLog();
    Code:
       0: aload_0
       1: getfield      #76                 // Field binding:Lcom/wuxianggujun/tinaide/databinding/BottomSheetPanelV2Binding;
       4: getfield      #216                // Field com/wuxianggujun/tinaide/databinding/BottomSheetPanelV2Binding.viewPager:Landroidx/viewpager2/widget/ViewPager2;
       7: iconst_0
       8: invokevirtual #541                // Method androidx/viewpager2/widget/ViewPager2.setCurrentItem:(I)V
      11: return

  public final void switchToGeneralLog();
    Code:
       0: aload_0
       1: getfield      #76                 // Field binding:Lcom/wuxianggujun/tinaide/databinding/BottomSheetPanelV2Binding;
       4: getfield      #216                // Field com/wuxianggujun/tinaide/databinding/BottomSheetPanelV2Binding.viewPager:Landroidx/viewpager2/widget/ViewPager2;
       7: iconst_1
       8: invokevirtual #541                // Method androidx/viewpager2/widget/ViewPager2.setCurrentItem:(I)V
      11: return

  public final void switchToDiagnostics();
    Code:
       0: aload_0
       1: getfield      #76                 // Field binding:Lcom/wuxianggujun/tinaide/databinding/BottomSheetPanelV2Binding;
       4: getfield      #216                // Field com/wuxianggujun/tinaide/databinding/BottomSheetPanelV2Binding.viewPager:Landroidx/viewpager2/widget/ViewPager2;
       7: iconst_2
       8: invokevirtual #541                // Method androidx/viewpager2/widget/ViewPager2.setCurrentItem:(I)V
      11: return

  public final void setDiagnostics(java.util.List<com.wuxianggujun.tinaide.lsp.model.Diagnostic>);
    Code:
       0: aload_1
       1: ldc_w         #548                // String diagnostics
       4: invokestatic  #16                 // Method kotlin/jvm/internal/Intrinsics.checkNotNullParameter:(Ljava/lang/Object;Ljava/lang/String;)V
       7: aload_0
       8: getfield      #309                // Field diagnosticsFragment:Lcom/wuxianggujun/tinaide/ui/fragment/DiagnosticsFragment;
      11: ifnull        74
      14: aload_0
      15: getfield      #309                // Field diagnosticsFragment:Lcom/wuxianggujun/tinaide/ui/fragment/DiagnosticsFragment;
      18: dup
      19: ifnonnull     30
      22: pop
      23: ldc_w         #549                // String diagnosticsFragment
      26: invokestatic  #231                // Method kotlin/jvm/internal/Intrinsics.throwUninitializedPropertyAccessException:(Ljava/lang/String;)V
      29: aconst_null
      30: invokevirtual #550                // Method com/wuxianggujun/tinaide/ui/fragment/DiagnosticsFragment.isAdded:()Z
      33: ifeq          74
      36: aload_0
      37: getfield      #309                // Field diagnosticsFragment:Lcom/wuxianggujun/tinaide/ui/fragment/DiagnosticsFragment;
      40: dup
      41: ifnonnull     52
      44: pop
      45: ldc_w         #549                // String diagnosticsFragment
      48: invokestatic  #231                // Method kotlin/jvm/internal/Intrinsics.throwUninitializedPropertyAccessException:(Ljava/lang/String;)V
      51: aconst_null
      52: invokevirtual #551                // Method com/wuxianggujun/tinaide/ui/fragment/DiagnosticsFragment.getView:()Landroid/view/View;
      55: dup
      56: ifnull        73
      59: aload_0
      60: aload_1
      61: invokedynamic #559,  0            // InvokeDynamic #16:run:(Lcom/wuxianggujun/tinaide/ui/BottomPanelManager;Ljava/util/List;)Ljava/lang/Runnable;
      66: invokevirtual #500                // Method android/view/View.post:(Ljava/lang/Runnable;)Z
      69: pop
      70: goto          74
      73: pop
      74: return

  public final void addDiagnostic(com.wuxianggujun.tinaide.lsp.model.Diagnostic);
    Code:
       0: aload_1
       1: ldc_w         #564                // String diagnostic
       4: invokestatic  #16                 // Method kotlin/jvm/internal/Intrinsics.checkNotNullParameter:(Ljava/lang/Object;Ljava/lang/String;)V
       7: aload_0
       8: getfield      #309                // Field diagnosticsFragment:Lcom/wuxianggujun/tinaide/ui/fragment/DiagnosticsFragment;
      11: ifnull        74
      14: aload_0
      15: getfield      #309                // Field diagnosticsFragment:Lcom/wuxianggujun/tinaide/ui/fragment/DiagnosticsFragment;
      18: dup
      19: ifnonnull     30
      22: pop
      23: ldc_w         #549                // String diagnosticsFragment
      26: invokestatic  #231                // Method kotlin/jvm/internal/Intrinsics.throwUninitializedPropertyAccessException:(Ljava/lang/String;)V
      29: aconst_null
      30: invokevirtual #550                // Method com/wuxianggujun/tinaide/ui/fragment/DiagnosticsFragment.isAdded:()Z
      33: ifeq          74
      36: aload_0
      37: getfield      #309                // Field diagnosticsFragment:Lcom/wuxianggujun/tinaide/ui/fragment/DiagnosticsFragment;
      40: dup
      41: ifnonnull     52
      44: pop
      45: ldc_w         #549                // String diagnosticsFragment
      48: invokestatic  #231                // Method kotlin/jvm/internal/Intrinsics.throwUninitializedPropertyAccessException:(Ljava/lang/String;)V
      51: aconst_null
      52: invokevirtual #551                // Method com/wuxianggujun/tinaide/ui/fragment/DiagnosticsFragment.getView:()Landroid/view/View;
      55: dup
      56: ifnull        73
      59: aload_0
      60: aload_1
      61: invokedynamic #572,  0            // InvokeDynamic #17:run:(Lcom/wuxianggujun/tinaide/ui/BottomPanelManager;Lcom/wuxianggujun/tinaide/lsp/model/Diagnostic;)Ljava/lang/Runnable;
      66: invokevirtual #500                // Method android/view/View.post:(Ljava/lang/Runnable;)Z
      69: pop
      70: goto          74
      73: pop
      74: return

  public final void clearDiagnostics();
    Code:
       0: aload_0
       1: getfield      #309                // Field diagnosticsFragment:Lcom/wuxianggujun/tinaide/ui/fragment/DiagnosticsFragment;
       4: ifnull        66
       7: aload_0
       8: getfield      #309                // Field diagnosticsFragment:Lcom/wuxianggujun/tinaide/ui/fragment/DiagnosticsFragment;
      11: dup
      12: ifnonnull     23
      15: pop
      16: ldc_w         #549                // String diagnosticsFragment
      19: invokestatic  #231                // Method kotlin/jvm/internal/Intrinsics.throwUninitializedPropertyAccessException:(Ljava/lang/String;)V
      22: aconst_null
      23: invokevirtual #550                // Method com/wuxianggujun/tinaide/ui/fragment/DiagnosticsFragment.isAdded:()Z
      26: ifeq          66
      29: aload_0
      30: getfield      #309                // Field diagnosticsFragment:Lcom/wuxianggujun/tinaide/ui/fragment/DiagnosticsFragment;
      33: dup
      34: ifnonnull     45
      37: pop
      38: ldc_w         #549                // String diagnosticsFragment
      41: invokestatic  #231                // Method kotlin/jvm/internal/Intrinsics.throwUninitializedPropertyAccessException:(Ljava/lang/String;)V
      44: aconst_null
      45: invokevirtual #551                // Method com/wuxianggujun/tinaide/ui/fragment/DiagnosticsFragment.getView:()Landroid/view/View;
      48: dup
      49: ifnull        65
      52: aload_0
      53: invokedynamic #579,  0            // InvokeDynamic #18:run:(Lcom/wuxianggujun/tinaide/ui/BottomPanelManager;)Ljava/lang/Runnable;
      58: invokevirtual #500                // Method android/view/View.post:(Ljava/lang/Runnable;)Z
      61: pop
      62: goto          66
      65: pop
      66: return

  public final void destroy();
    Code:
       0: aload_0
       1: getfield      #361                // Field initListener:Lcom/wuxianggujun/tinaide/lsp/LspService$InitializationListener;
       4: dup
       5: ifnull        21
       8: astore_1
       9: iconst_0
      10: istore_2
      11: getstatic     #382                // Field com/wuxianggujun/tinaide/lsp/LspService.INSTANCE:Lcom/wuxianggujun/tinaide/lsp/LspService;
      14: aload_1
      15: invokevirtual #583                // Method com/wuxianggujun/tinaide/lsp/LspService.removeInitializationListener:(Lcom/wuxianggujun/tinaide/lsp/LspService$InitializationListener;)V
      18: goto          23
      21: pop
      22: nop
      23: aload_0
      24: getfield      #376                // Field healthListener:Lcom/wuxianggujun/tinaide/lsp/LspService$HealthListener;
      27: dup
      28: ifnull        44
      31: astore_1
      32: iconst_0
      33: istore_2
      34: getstatic     #382                // Field com/wuxianggujun/tinaide/lsp/LspService.INSTANCE:Lcom/wuxianggujun/tinaide/lsp/LspService;
      37: aload_1
      38: invokevirtual #586                // Method com/wuxianggujun/tinaide/lsp/LspService.removeHealthListener:(Lcom/wuxianggujun/tinaide/lsp/LspService$HealthListener;)V
      41: goto          46
      44: pop
      45: nop
      46: return

  private final int dpToPx(int);
    Code:
       0: aload_0
       1: getfield      #37                 // Field container:Landroid/view/ViewGroup;
       4: invokevirtual #55                 // Method android/view/ViewGroup.getContext:()Landroid/content/Context;
       7: invokevirtual #592                // Method android/content/Context.getResources:()Landroid/content/res/Resources;
      10: invokevirtual #598                // Method android/content/res/Resources.getDisplayMetrics:()Landroid/util/DisplayMetrics;
      13: getfield      #604                // Field android/util/DisplayMetrics.density:F
      16: fstore_2
      17: iload_1
      18: i2f
      19: fload_2
      20: fmul
      21: f2i
      22: ireturn

  private static final kotlin.Unit _init_$lambda$0();
    Code:
       0: getstatic     #610                // Field kotlin/Unit.INSTANCE:Lkotlin/Unit;
       3: areturn

  private static final kotlin.Unit _init_$lambda$1();
    Code:
       0: getstatic     #610                // Field kotlin/Unit.INSTANCE:Lkotlin/Unit;
       3: areturn

  private static final kotlin.Unit _init_$lambda$2();
    Code:
       0: getstatic     #610                // Field kotlin/Unit.INSTANCE:Lkotlin/Unit;
       3: areturn

  private static final kotlin.Unit _init_$lambda$3(com.wuxianggujun.tinaide.lsp.model.Diagnostic);
    Code:
       0: aload_0
       1: ldc_w         #611                // String it
       4: invokestatic  #16                 // Method kotlin/jvm/internal/Intrinsics.checkNotNullParameter:(Ljava/lang/Object;Ljava/lang/String;)V
       7: getstatic     #610                // Field kotlin/Unit.INSTANCE:Lkotlin/Unit;
      10: areturn

  private static final kotlin.Unit _init_$lambda$4(java.lang.String);
    Code:
       0: aload_0
       1: ldc_w         #611                // String it
       4: invokestatic  #16                 // Method kotlin/jvm/internal/Intrinsics.checkNotNullParameter:(Ljava/lang/Object;Ljava/lang/String;)V
       7: getstatic     #610                // Field kotlin/Unit.INSTANCE:Lkotlin/Unit;
      10: areturn

  private static final kotlin.Unit setupSymbolBar$lambda$6(com.wuxianggujun.tinaide.ui.BottomPanelManager, java.lang.String);
    Code:
       0: aload_1
       1: ldc_w         #613                // String symbol
       4: invokestatic  #16                 // Method kotlin/jvm/internal/Intrinsics.checkNotNullParameter:(Ljava/lang/Object;Ljava/lang/String;)V
       7: aload_0
       8: getfield      #49                 // Field onSymbolClick:Lkotlin/jvm/functions/Function1;
      11: aload_1
      12: invokeinterface #617,  2          // InterfaceMethod kotlin/jvm/functions/Function1.invoke:(Ljava/lang/Object;)Ljava/lang/Object;
      17: pop
      18: getstatic     #610                // Field kotlin/Unit.INSTANCE:Lkotlin/Unit;
      21: areturn

  private static final kotlin.Unit setupTabs$lambda$7(com.wuxianggujun.tinaide.ui.BottomPanelManager);
    Code:
       0: aload_0
       1: getfield      #526                // Field buildSucceeded:Z
       4: ifeq          20
       7: aload_0
       8: getfield      #44                 // Field onOpenOutput:Lkotlin/jvm/functions/Function0;
      11: invokeinterface #622,  1          // InterfaceMethod kotlin/jvm/functions/Function0.invoke:()Ljava/lang/Object;
      16: pop
      17: goto          40
      20: aload_0
      21: getfield      #37                 // Field container:Landroid/view/ViewGroup;
      24: invokevirtual #55                 // Method android/view/ViewGroup.getContext:()Landroid/content/Context;
      27: ldc_w         #624                // String ąą˝¨Ę§°ÜŁ¬ÎŢ·¨´ňżŞĘäłö˝çĂć
      30: checkcast     #448                // class java/lang/CharSequence
      33: iconst_0
      34: invokestatic  #630                // Method android/widget/Toast.makeText:(Landroid/content/Context;Ljava/lang/CharSequence;I)Landroid/widget/Toast;
      37: invokevirtual #633                // Method android/widget/Toast.show:()V
      40: getstatic     #610                // Field kotlin/Unit.INSTANCE:Lkotlin/Unit;
      43: areturn

  private static final void setupTabs$lambda$8(com.google.android.material.tabs.TabLayout$Tab, int);
    Code:
       0: aload_0
       1: ldc_w         #635                // String tab
       4: invokestatic  #16                 // Method kotlin/jvm/internal/Intrinsics.checkNotNullParameter:(Ljava/lang/Object;Ljava/lang/String;)V
       7: aload_0
       8: iload_1
       9: tableswitch   { // 0 to 2
                     0: 36
                     1: 42
                     2: 48
               default: 54
          }
      36: ldc_w         #637                // String ąą˝¨ČŐÖľ
      39: goto          57
      42: ldc_w         #639                // String ČŐÖľ
      45: goto          57
      48: ldc_w         #641                // String Őď¶Ď
      51: goto          57
      54: ldc_w         #643                // String
      57: checkcast     #448                // class java/lang/CharSequence
      60: invokevirtual #648                // Method com/google/android/material/tabs/TabLayout$Tab.setText:(Ljava/lang/CharSequence;)Lcom/google/android/material/tabs/TabLayout$Tab;
      63: pop
      64: return

  private static final void setupLspStatus$lambda$10$lambda$9(boolean, com.wuxianggujun.tinaide.ui.BottomPanelManager);
    Code:
       0: iload_0
       1: ifeq          10
       4: ldc_w         #395                // String LSP
       7: goto          13
      10: ldc_w         #395                // String LSP
      13: astore_2
      14: aload_1
      15: iload_0
      16: aload_2
      17: invokespecial #399                // Method updateLspStatus:(ZLjava/lang/String;)V
      20: return

  private static final void setupLspStatus$lambda$10(com.wuxianggujun.tinaide.ui.BottomPanelManager, boolean);
    Code:
       0: aload_0
       1: getfield      #76                 // Field binding:Lcom/wuxianggujun/tinaide/databinding/BottomSheetPanelV2Binding;
       4: invokevirtual #411                // Method com/wuxianggujun/tinaide/databinding/BottomSheetPanelV2Binding.getRoot:()Landroidx/coordinatorlayout/widget/CoordinatorLayout;
       7: iload_1
       8: aload_0
       9: invokedynamic #661,  0            // InvokeDynamic #19:run:(ZLcom/wuxianggujun/tinaide/ui/BottomPanelManager;)Ljava/lang/Runnable;
      14: invokevirtual #662                // Method androidx/coordinatorlayout/widget/CoordinatorLayout.post:(Ljava/lang/Runnable;)Z
      17: pop
      18: return

  private static final void setupLspStatus$lambda$12$lambda$11(com.wuxianggujun.tinaide.ui.BottomPanelManager);
    Code:
       0: aload_0
       1: iconst_0
       2: ldc_w         #395                // String LSP
       5: invokespecial #399                // Method updateLspStatus:(ZLjava/lang/String;)V
       8: return

  private static final void setupLspStatus$lambda$12(com.wuxianggujun.tinaide.ui.BottomPanelManager, com.wuxianggujun.tinaide.lsp.LspService$HealthEventType, java.lang.String);
    Code:
       0: aload_1
       1: ldc_w         #665                // String type
       4: invokestatic  #16                 // Method kotlin/jvm/internal/Intrinsics.checkNotNullParameter:(Ljava/lang/Object;Ljava/lang/String;)V
       7: aload_2
       8: ldc_w         #482                // String message
      11: invokestatic  #16                 // Method kotlin/jvm/internal/Intrinsics.checkNotNullParameter:(Ljava/lang/Object;Ljava/lang/String;)V
      14: aload_0
      15: getfield      #76                 // Field binding:Lcom/wuxianggujun/tinaide/databinding/BottomSheetPanelV2Binding;
      18: invokevirtual #411                // Method com/wuxianggujun/tinaide/databinding/BottomSheetPanelV2Binding.getRoot:()Landroidx/coordinatorlayout/widget/CoordinatorLayout;
      21: aload_0
      22: invokedynamic #669,  0            // InvokeDynamic #20:run:(Lcom/wuxianggujun/tinaide/ui/BottomPanelManager;)Ljava/lang/Runnable;
      27: invokevirtual #662                // Method androidx/coordinatorlayout/widget/CoordinatorLayout.post:(Ljava/lang/Runnable;)Z
      30: pop
      31: return

  private static final boolean setupGestureDetector$lambda$15(com.wuxianggujun.tinaide.ui.BottomPanelManager, android.view.View, android.view.MotionEvent);
    Code:
       0: aload_0
       1: getfield      #132                // Field gestureDetector:Landroid/view/GestureDetector;
       4: aload_2
       5: invokevirtual #674                // Method android/view/GestureDetector.onTouchEvent:(Landroid/view/MotionEvent;)Z
       8: pop
       9: iconst_0
      10: ireturn

  private static final void appendBuildLog$lambda$16(com.wuxianggujun.tinaide.ui.BottomPanelManager, com.wuxianggujun.tinaide.output.LogLevel, java.lang.String);
    Code:
       0: aload_0
       1: getfield      #226                // Field buildLogFragment:Lcom/wuxianggujun/tinaide/ui/fragment/BuildLogFragment;
       4: dup
       5: ifnonnull     15
       8: pop
       9: ldc           #227                // String buildLogFragment
      11: invokestatic  #231                // Method kotlin/jvm/internal/Intrinsics.throwUninitializedPropertyAccessException:(Ljava/lang/String;)V
      14: aconst_null
      15: aload_1
      16: aload_2
      17: invokevirtual #679                // Method com/wuxianggujun/tinaide/ui/fragment/BuildLogFragment.appendLog:(Lcom/wuxianggujun/tinaide/output/LogLevel;Ljava/lang/String;)V
      20: return

  private static final void appendGeneralLog$lambda$17(com.wuxianggujun.tinaide.ui.BottomPanelManager, com.wuxianggujun.tinaide.output.LogLevel, java.lang.String);
    Code:
       0: aload_0
       1: getfield      #244                // Field generalLogFragment:Lcom/wuxianggujun/tinaide/ui/fragment/GeneralLogFragment;
       4: dup
       5: ifnonnull     15
       8: pop
       9: ldc           #245                // String generalLogFragment
      11: invokestatic  #231                // Method kotlin/jvm/internal/Intrinsics.throwUninitializedPropertyAccessException:(Ljava/lang/String;)V
      14: aconst_null
      15: aload_1
      16: aload_2
      17: invokevirtual #682                // Method com/wuxianggujun/tinaide/ui/fragment/GeneralLogFragment.appendLog:(Lcom/wuxianggujun/tinaide/output/LogLevel;Ljava/lang/String;)V
      20: return

  private static final void clearBuildLog$lambda$18(com.wuxianggujun.tinaide.ui.BottomPanelManager);
    Code:
       0: aload_0
       1: getfield      #226                // Field buildLogFragment:Lcom/wuxianggujun/tinaide/ui/fragment/BuildLogFragment;
       4: dup
       5: ifnonnull     15
       8: pop
       9: ldc           #227                // String buildLogFragment
      11: invokestatic  #231                // Method kotlin/jvm/internal/Intrinsics.throwUninitializedPropertyAccessException:(Ljava/lang/String;)V
      14: aconst_null
      15: invokevirtual #685                // Method com/wuxianggujun/tinaide/ui/fragment/BuildLogFragment.clearLog:()V
      18: return

  private static final void clearGeneralLog$lambda$19(com.wuxianggujun.tinaide.ui.BottomPanelManager);
    Code:
       0: aload_0
       1: getfield      #244                // Field generalLogFragment:Lcom/wuxianggujun/tinaide/ui/fragment/GeneralLogFragment;
       4: dup
       5: ifnonnull     15
       8: pop
       9: ldc           #245                // String generalLogFragment
      11: invokestatic  #231                // Method kotlin/jvm/internal/Intrinsics.throwUninitializedPropertyAccessException:(Ljava/lang/String;)V
      14: aconst_null
      15: invokevirtual #686                // Method com/wuxianggujun/tinaide/ui/fragment/GeneralLogFragment.clearLog:()V
      18: return

  private static final void setBuildSucceeded$lambda$20(com.wuxianggujun.tinaide.ui.BottomPanelManager, boolean);
    Code:
       0: aload_0
       1: getfield      #226                // Field buildLogFragment:Lcom/wuxianggujun/tinaide/ui/fragment/BuildLogFragment;
       4: dup
       5: ifnonnull     15
       8: pop
       9: ldc           #227                // String buildLogFragment
      11: invokestatic  #231                // Method kotlin/jvm/internal/Intrinsics.throwUninitializedPropertyAccessException:(Ljava/lang/String;)V
      14: aconst_null
      15: iload_1
      16: invokevirtual #689                // Method com/wuxianggujun/tinaide/ui/fragment/BuildLogFragment.setOutputButtonEnabled:(Z)V
      19: return

  private static final void setDiagnostics$lambda$21(com.wuxianggujun.tinaide.ui.BottomPanelManager, java.util.List);
    Code:
       0: aload_0
       1: getfield      #309                // Field diagnosticsFragment:Lcom/wuxianggujun/tinaide/ui/fragment/DiagnosticsFragment;
       4: dup
       5: ifnonnull     16
       8: pop
       9: ldc_w         #549                // String diagnosticsFragment
      12: invokestatic  #231                // Method kotlin/jvm/internal/Intrinsics.throwUninitializedPropertyAccessException:(Ljava/lang/String;)V
      15: aconst_null
      16: aload_1
      17: invokevirtual #692                // Method com/wuxianggujun/tinaide/ui/fragment/DiagnosticsFragment.setDiagnostics:(Ljava/util/List;)V
      20: return

  private static final void addDiagnostic$lambda$22(com.wuxianggujun.tinaide.ui.BottomPanelManager, com.wuxianggujun.tinaide.lsp.model.Diagnostic);
    Code:
       0: aload_0
       1: getfield      #309                // Field diagnosticsFragment:Lcom/wuxianggujun/tinaide/ui/fragment/DiagnosticsFragment;
       4: dup
       5: ifnonnull     16
       8: pop
       9: ldc_w         #549                // String diagnosticsFragment
      12: invokestatic  #231                // Method kotlin/jvm/internal/Intrinsics.throwUninitializedPropertyAccessException:(Ljava/lang/String;)V
      15: aconst_null
      16: aload_1
      17: invokevirtual #695                // Method com/wuxianggujun/tinaide/ui/fragment/DiagnosticsFragment.addDiagnostic:(Lcom/wuxianggujun/tinaide/lsp/model/Diagnostic;)V
      20: return

  private static final void clearDiagnostics$lambda$23(com.wuxianggujun.tinaide.ui.BottomPanelManager);
    Code:
       0: aload_0
       1: getfield      #309                // Field diagnosticsFragment:Lcom/wuxianggujun/tinaide/ui/fragment/DiagnosticsFragment;
       4: dup
       5: ifnonnull     16
       8: pop
       9: ldc_w         #549                // String diagnosticsFragment
      12: invokestatic  #231                // Method kotlin/jvm/internal/Intrinsics.throwUninitializedPropertyAccessException:(Ljava/lang/String;)V
      15: aconst_null
      16: invokevirtual #698                // Method com/wuxianggujun/tinaide/ui/fragment/DiagnosticsFragment.clearDiagnostics:()V
      19: return

  public static final com.wuxianggujun.tinaide.databinding.BottomSheetPanelV2Binding access$getBinding$p(com.wuxianggujun.tinaide.ui.BottomPanelManager);
    Code:
       0: aload_0
       1: getfield      #76                 // Field binding:Lcom/wuxianggujun/tinaide/databinding/BottomSheetPanelV2Binding;
       4: areturn

  public static final void access$notifyLogViewsVisibility(com.wuxianggujun.tinaide.ui.BottomPanelManager, boolean);
    Code:
       0: aload_0
       1: iload_1
       2: invokespecial #704                // Method notifyLogViewsVisibility:(Z)V
       5: return

  public static final com.wuxianggujun.tinaide.ui.fragment.BuildLogFragment access$getBuildLogFragment$p(com.wuxianggujun.tinaide.ui.BottomPanelManager);
    Code:
       0: aload_0
       1: getfield      #226                // Field buildLogFragment:Lcom/wuxianggujun/tinaide/ui/fragment/BuildLogFragment;
       4: areturn

  public static final com.wuxianggujun.tinaide.ui.fragment.GeneralLogFragment access$getGeneralLogFragment$p(com.wuxianggujun.tinaide.ui.BottomPanelManager);
    Code:
       0: aload_0
       1: getfield      #244                // Field generalLogFragment:Lcom/wuxianggujun/tinaide/ui/fragment/GeneralLogFragment;
       4: areturn

  public static final com.wuxianggujun.tinaide.ui.fragment.DiagnosticsFragment access$getDiagnosticsFragment$p(com.wuxianggujun.tinaide.ui.BottomPanelManager);
    Code:
       0: aload_0
       1: getfield      #309                // Field diagnosticsFragment:Lcom/wuxianggujun/tinaide/ui/fragment/DiagnosticsFragment;
       4: areturn
}
